gaforecast/__init__.py
gaforecast/models/__init__.py
gaforecast/models/binary_classifier.py
gaforecast/models/regressor.py
gaforecast-0.3.0.dist-info/LICENSE
gaforecast-0.3.0.dist-info/METADATA
gaforecast-0.3.0.dist-info/WHEEL
gaforecast-0.3.0.dist-info/RECORD
